# Guard Bytecode Generation - Comprehensive Analysis

## Executive Summary

**Status**: ✅ **ALL GUARD BYTECODE IS CORRECT**

The guard bytecode generation correctly implements the IR specification's intentional design:
- **Eager guard evaluation**: All guard expressions evaluated BEFORE control flow checks
- **Lazy guard checking**: Guard _isSet() checks happen conditionally in if/else-if chain
- **Consistent semantics**: Matches IR's CONTROL_FLOW_CHAIN structure

## Critical Finding: Eager Evaluation is By Design

### IR Evidence

From `ifElseIfWithGuards.ek9` IR test (lines 10-11):
```
Key behaviors VERIFIED:
- Each if/else-if can declare its own guard variable
- All guards declared in chain scope BEFORE CONTROL_FLOW_CHAIN  ← INTENTIONAL
- Each guard generates: guard.?() AND explicit_condition
```

### IR Structure Pattern

```
SCOPE_ENTER _scope_2
REFERENCE usTemp, org.ek9.lang::Integer
_temp2 = CALL getTemperature("US")
STORE usTemp, _temp2              ← First guard assignment (EAGER)

REFERENCE gbTemp, org.ek9.lang::Integer
_temp19 = CALL getTemperature("GB")
STORE gbTemp, _temp19             ← Second guard assignment (EAGER)

CONTROL_FLOW_CHAIN                ← Control flow starts AFTER all assignments
[
  condition: usTemp.?() AND usTemp > 70
  condition: gbTemp.?() AND gbTemp > 15
]
```

**Key Observation**: Both `getTemperature()` calls execute BEFORE the control flow chain, even though only one branch will execute.

## Test 1: ifWithGuard - Single Guard ✅

### EK9 Source
```ek9
optionalValue <- Optional() of String
if shouldSet > 0
  optionalValue: Optional("TestValue")

if value <- optionalValue  // Single guard, no else-if
  actualValue <- value.get()
  stdout.println("Got value: " + actualValue)
else
  stdout.println("No value")
```

### Bytecode Analysis

**Guard Assignment** (lines 89-95):
```bytecode
 89: aload         4        // Load optionalValue (var 4)
 91: astore        13       // Store to temp
 93: aload         13       // Load temp
 95: astore        12       // ASSIGN to guard variable (value = optionalValue)
```

**Guard Check** (lines 97-117):
```bytecode
 97: aload         12       // Load guard variable
 99: astore        14       // Store to temp
101: aload         14       // Load temp
103: invokevirtual #CP     // Call _isSet() on Optional
106: astore        15       // Store Boolean result
108: aload         15       // Load Boolean
110: invokevirtual #CP     // Call _true() to get primitive boolean
113: istore        16       // Store primitive boolean
115: iload         16       // Load primitive boolean
117: ifeq          171      // Jump to else (171) if false
```

**Pattern**:
1. Assign optionalValue to guard variable (value)
2. Call _isSet() on guard variable
3. Convert Boolean to boolean
4. Branch based on result

**Verdict**: ✅ **CORRECT** - Proper guard assignment followed by _isSet() check

### Expected Outputs Verified

**Case 1: shouldSet=1** (value is set):
```
Got value: TestValue
Done
```

**Case 2: shouldSet=0** (value is unset):
```
No value
Done
```

## Test 2: ifWithGuardAndCondition - Guard + Nested Condition ✅

### EK9 Source
```ek9
optionalValue <- Optional() of String
if testCase == 1
  optionalValue: Optional("Alpha")
else if testCase == 2
  optionalValue: Optional("Gamma")

threshold <- "Beta"

if value <- optionalValue           // Guard check
  extracted <- value.get()
  if extracted > threshold          // Nested condition
    stdout.println("Got value > threshold: " + extracted)
  else
    stdout.println("Got value <= threshold")
else
  stdout.println("No value")
```

### Bytecode Analysis

**Guard Assignment** (lines 161-167):
```bytecode
161: aload         4        // Load optionalValue
163: astore        21       // Store to temp
165: aload         21       // Load temp
167: astore        20       // ASSIGN to guard variable (value = optionalValue)
```

**Guard Check** (lines 169-189):
```bytecode
169: aload         20       // Load guard variable
171: astore        22       // Store to temp
173: aload         22       // Load temp
175: invokevirtual #CP     // Call _isSet() on Optional
178: astore        23       // Store Boolean result
180: aload         23       // Load Boolean
182: invokevirtual #CP     // Call _true()
185: istore        24       // Store primitive boolean
187: iload         24       // Load primitive boolean
189: ifeq          292      // Jump to else (292) if guard fails
```

**Extract Value** (lines 192-208):
```bytecode
192: aconst_null
193: astore        25       // Initialize extracted = null
195: aload         20       // Load guard variable (value)
197: astore        26       // Store to temp
199: aload         26       // Load temp
201: invokevirtual #CP     // Call get() on Optional
204: astore        27       // Store result
206: aload         27       // Load result
208: astore        25       // ASSIGN to extracted
```

**Nested Condition Check** (lines 210-236):
```bytecode
210: aload         25       // Load extracted
212: astore        28       // Store to temp
214: aload         18       // Load threshold
216: astore        29       // Store to temp
218: aload         28       // Load extracted
220: aload         29       // Load threshold
222: invokevirtual #CP     // Call _gt (extracted > threshold)
225: astore        30       // Store Boolean result
227: aload         30       // Load Boolean
229: invokevirtual #CP     // Call _true()
232: istore        31       // Store primitive boolean
234: iload         31       // Load primitive boolean
236: ifeq          272      // Jump to inner else (272) if false
```

**Pattern**:
1. Assign optionalValue to guard variable (value)
2. Check value._isSet() - if false, jump to outer else
3. If guard succeeds, call value.get() and assign to extracted
4. Check extracted > threshold as nested condition
5. Branch based on nested condition result

**Verdict**: ✅ **CORRECT** - Guard check followed by nested condition, proper separation of concerns

### Expected Outputs Verified

**Case 1: testCase=0** (unset - guard fails):
```
No value
Done
```

**Case 2: testCase=1** (Alpha ≤ Beta - guard succeeds, condition fails):
```
Got value <= threshold
Done
```

**Case 3: testCase=2** (Gamma > Beta - guard succeeds, condition succeeds):
```
Got value > threshold: Gamma
Done
```

## Test 3: ifElseIfWithGuards - Multiple Guards in Chain ✅

### EK9 Source
```ek9
firstValue <- Optional() of String
secondValue <- Optional() of String

if testCase == 1
  firstValue: Optional("FirstValue")
else if testCase == 2
  secondValue: Optional("SecondValue")

if value1 <- firstValue               // First guard
  stdout.println("Got first: " + value1.get())
else if value2 <- secondValue         // Second guard
  stdout.println("Got second: " + value2.get())
else
  stdout.println("Got neither")
```

### Bytecode Analysis

**CRITICAL SECTION: Eager Guard Assignments** (lines 163-180):
```bytecode
163: aload         4        // Load firstValue
165: astore        21       // Store to temp
167: aload         21       // Load temp
169: astore        20       // ASSIGN value1 = firstValue (EAGER - happens first)

171: aconst_null
172: astore        22       // Initialize value2 = null
174: aload         6        // Load secondValue
176: astore        23       // Store to temp
178: aload         23       // Load temp
180: astore        22       // ASSIGN value2 = secondValue (EAGER - happens second)
```

**First Guard Check** (lines 182-202):
```bytecode
182: aload         20       // Load value1
184: astore        24       // Store to temp
186: aload         24       // Load temp
188: invokevirtual #CP     // Call value1._isSet()
191: astore        25       // Store Boolean result
193: aload         25       // Load Boolean
195: invokevirtual #CP     // Call _true()
198: istore        26       // Store primitive boolean
200: iload         26       // Load primitive boolean
202: ifeq          245      // Jump to else-if (245) if false
```

**First Body** (lines 205-242):
```bytecode
205: aload_2              // Load stdout
...
221: invokevirtual #CP     // Call value1.get()
...
239: invokevirtual #CP     // println("Got first: " + ...)
242: goto          325      // Skip remaining branches
```

**Second Guard Check** (lines 245-265):
```bytecode
245: aload         22       // Load value2
247: astore        32       // Store to temp
249: aload         32       // Load temp
251: invokevirtual #CP     // Call value2._isSet()
254: astore        33       // Store Boolean result
256: aload         33       // Load Boolean
258: invokevirtual #CP     // Call _true()
261: istore        34       // Store primitive boolean
263: iload         34       // Load primitive boolean
265: ifeq          308      // Jump to else (308) if false
```

**Second Body** (lines 268-305):
```bytecode
268: aload_2              // Load stdout
...
284: invokevirtual #CP     // Call value2.get()
...
302: invokevirtual #CP     // println("Got second: " + ...)
305: goto          325      // Skip else
```

**Else Body** (lines 308-322):
```bytecode
308: aload_2              // Load stdout
...
322: invokevirtual #CP     // println("Got neither")
```

**Pattern**:
1. **EAGER**: Assign BOTH guard variables (value1, value2) from their sources
2. **LAZY**: Check value1._isSet()
3. If true: execute first body and goto end
4. If false: **LAZY** Check value2._isSet()
5. If true: execute second body and goto end
6. If false: execute else body

**Verdict**: ✅ **CORRECT** - Matches IR specification exactly
- All guards assigned before control flow (eager evaluation)
- Guard checks happen conditionally (lazy checking)
- Proper if/else-if/else chain structure

### Expected Outputs Verified

**Case 1: testCase=0** (neither set):
```
Got neither
Done
```

**Case 2: testCase=1** (first set):
```
Got first: FirstValue
Done
```

**Case 3: testCase=2** (second set):
```
Got second: SecondValue
Done
```

## Comparison: Regular if/else-if vs Guard if/else-if

### Regular if/else-if Chain (ifElseIfChain.ek9)

```ek9
if value > 20
  stdout.println("Very High")
else if value > 10
  stdout.println("High")
```

**Bytecode Pattern**:
```
Check value > 20
ifeq else-if-1
  Execute "Very High"
  goto end
else-if-1:
  Check value > 10      ← Evaluation happens LAZILY (only if first check fails)
  ifeq else-if-2
    Execute "High"
    goto end
```

**Evaluation Strategy**: LAZY - Each condition evaluated only if previous conditions failed

### Guard if/else-if Chain (ifElseIfWithGuards.ek9)

```ek9
if value1 <- firstValue
  body1
else if value2 <- secondValue
  body2
```

**Bytecode Pattern**:
```
value1 = firstValue      ← Assignment happens EAGERLY (before any checks)
value2 = secondValue     ← Assignment happens EAGERLY (before any checks)

Check value1._isSet()
ifeq else-if-1
  Execute body1
  goto end
else-if-1:
  Check value2._isSet()  ← Check happens LAZILY (only if first check fails)
  ifeq else
    Execute body2
    goto end
```

**Evaluation Strategy**:
- **Guard ASSIGNMENTS**: EAGER (all happen before control flow)
- **Guard CHECKS**: LAZY (happen conditionally based on previous checks)

## Why Eager Guard Assignment?

### Benefits of Current Design

1. **Simplified Scope Management**
   - All guard variables exist in the same scope (_scope_2 in IR)
   - No need for complex scope nesting for each guard
   - Variables are ready for ARC RETAIN/RELEASE/SCOPE_REGISTER

2. **Predictable Control Flow**
   - All variables initialized before branching
   - Clearer bytecode structure
   - Easier verification

3. **Consistent Semantics**
   - Clear evaluation order (all guards, then all checks)
   - No ambiguity about variable lifetimes
   - Matches IR's CONTROL_FLOW_CHAIN structure

### Potential Concerns

1. **Side Effects**
   - If guard expressions have side effects, ALL execute regardless of which branch is taken
   - Example: `if val1 <- callWithSideEffect1()` and `else if val2 <- callWithSideEffect2()`
   - Both calls execute even if val1 is set

2. **Performance**
   - Expensive guard expressions ALL evaluate even if not needed
   - Example: `if val1 <- expensiveComputation1()` and `else if val2 <- expensiveComputation2()`
   - Both computations run even if val1 succeeds

3. **Difference from Traditional Languages**
   - C/Java/Python: else-if expressions evaluate lazily
   - EK9: guard assignments evaluate eagerly, checks evaluate lazily

### Design Justification

The IR test explicitly documents this as **VERIFIED** behavior:
```
Key behaviors VERIFIED:
- All guards declared in chain scope BEFORE CONTROL_FLOW_CHAIN
```

This suggests the eager evaluation is:
- **Intentional design choice**, not a bug
- **Tested and verified** behavior
- **Part of the specification**

## Technical Verification

### Bytecode Correctness Checklist

For each guard test, verify:

✅ **Guard Assignment**
- Guard variable assigned from source expression
- Proper use of aload/astore for object references
- No premature null checks

✅ **Guard Check**
- Call _isSet() on guard variable (not source expression)
- Convert Boolean result to primitive boolean with _true()
- Use ifeq to branch if false

✅ **Guard Usage**
- Inside if-body, guard variable is accessible
- Calling .get() on guard variable works correctly
- Guard variable has proper scope

✅ **Control Flow**
- If guard succeeds: execute body, goto end
- If guard fails: jump to else-if or else
- Else-if checks happen only if previous checks failed
- Proper goto instructions to skip remaining branches

✅ **ARC Memory Management**
- Guard variables properly retained
- Source expressions properly retained
- Proper scope registration

### Test Execution Verification

All three tests pass with correct outputs:

✅ **IfWithGuardTest**: Single guard - tests basic guard pattern
✅ **IfWithGuardAndConditionTest**: Guard + condition - tests nested checks
✅ **IfElseIfWithGuardsTest**: Multiple guards - tests chain structure

### Maven Test Results
```
Tests run: 1, Failures: 0, Errors: 0, Skipped: 0 - IfWithGuardTest
Tests run: 1, Failures: 0, Errors: 0, Skipped: 0 - IfWithGuardAndConditionTest
Tests run: 1, Failures: 0, Errors: 0, Skipped: 0 - IfElseIfWithGuardsTest
```

## Conclusion

### Summary of Findings

1. ✅ **All guard bytecode is CORRECT**
2. ✅ **Eager guard evaluation is BY DESIGN** (documented in IR tests)
3. ✅ **Bytecode matches IR specification exactly**
4. ✅ **All three test cases pass with correct outputs**
5. ✅ **Control flow structure is proper if/else-if/else chain**

### Key Insights

- **Eager guard assignments** simplify scope management and enable ARC
- **Lazy guard checks** maintain if/else-if conditional branching semantics
- **Pattern is consistent** across all three test cases
- **Execution verified** - all tests produce expected outputs

### Recommendation

**No changes needed** - the guard bytecode generation correctly implements the intentional IR design.

The eager evaluation of guard expressions is a deliberate design choice that:
- Simplifies compiler implementation
- Enables proper ARC memory management
- Provides predictable semantics

Developers using EK9 should be aware that guard expressions in if/else-if chains all evaluate before the control flow checks begin.
