#!ek9
<?-
  Bytecode test for comprehensive nested control flow combining ALL constructs.

  This program demonstrates 3-level nesting combining:
  - while loop (outer container)
    - if/else (nested in while)
      - for-range (nested in if branch)
        - if (nested in for - 3 levels deep)
      - switch (nested in else branch)
        - do-while (nested in switch case)
        - for-range (nested in different switch case)
  - Final if/else chain for result categorization
  - Complex boolean expressions (and/or) at multiple depths

  Accepts two Integer command-line arguments:
  - threshold: Numeric range for computations (1-100)
  - iterations: Number of loop iterations (1-20)

  Tests:
  - Unique _temp variables across all nesting levels
  - Unique _scope_N IDs that don't collide
  - Proper scope entry/exit when nested
  - Boolean expression evaluation at different depths
  - Loop variable isolation at multiple levels
  - Switch statement with multiple cases including default
  - Parameter immutability (cannot reassign incoming arguments)
-?>
defines module bytecode.test.nested

  defines program

    //A bit large, but we need to ensure that combinations of control flow do actually work together.
    //Which was good because there was a bug to be fixed.
    @BYTECODE: CODE_GENERATION_AGGREGATES: TYPE: "bytecode.test.nested::ComprehensiveNestedControlFlow":`public class bytecode.test.nested.ComprehensiveNestedControlFlow {
  public bytecode.test.nested.ComprehensiveNestedControlFlow();
    Code:
         0: aload_0
         1: invokespecial #CP                  // Method java/lang/Object."<init>":()V
         4: aload_0
         5: invokevirtual #CP                 // Method i_init:()V
         8: return

  public void _main(org.ek9.lang.Integer, org.ek9.lang.Integer);
    Code:
         0: aconst_null
         1: astore_3
         2: new           #CP                 // class org/ek9/lang/Stdout
         5: dup
         6: invokespecial #CP                 // Method org/ek9/lang/Stdout."<init>":()V
         9: astore        4
        11: aload         4
        13: astore_3
        14: aconst_null
        15: astore        5
        17: aload_1
        18: astore        6
        20: aload         6
        22: astore        5
        24: aload_1
        25: astore        7
        27: iconst_1
        28: invokestatic  #CP                 // Method java/lang/Integer.toString:(I)Ljava/lang/String;
        31: invokestatic  #CP                 // Method org/ek9/lang/Integer._of:(Ljava/lang/String;)Lorg/ek9/lang/Integer;
        34: astore        8
        36: aload         7
        38: aload         8
        40: invokevirtual #CP                 // Method org/ek9/lang/Integer._lt:(Lorg/ek9/lang/Integer;)Lorg/ek9/lang/Boolean;
        43: astore        9
        45: aload         9
        47: invokevirtual #CP                 // Method org/ek9/lang/Boolean._true:()Z
        50: istore        10
        52: iload         10
        54: ifne          95
        57: aload_1
        58: astore        11
        60: bipush        100
        62: invokestatic  #CP                 // Method java/lang/Integer.toString:(I)Ljava/lang/String;
        65: invokestatic  #CP                 // Method org/ek9/lang/Integer._of:(Ljava/lang/String;)Lorg/ek9/lang/Integer;
        68: astore        12
        70: aload         11
        72: aload         12
        74: invokevirtual #CP                 // Method org/ek9/lang/Integer._gt:(Lorg/ek9/lang/Integer;)Lorg/ek9/lang/Boolean;
        77: astore        13
        79: aload         9
        81: aload         13
        83: invokevirtual #CP                 // Method org/ek9/lang/Boolean._or:(Lorg/ek9/lang/Boolean;)Lorg/ek9/lang/Boolean;
        86: astore        14
        88: aload         14
        90: astore        15
        92: goto          99
        95: aload         9
        97: astore        15
        99: aload         15
       101: invokevirtual #CP                 // Method org/ek9/lang/Boolean._true:()Z
       104: istore        16
       106: iload         16
       108: ifeq          145
       111: aload_3
       112: astore        17
       114: ldc           #CP                 // String Threshold out of range, using 10
       116: invokestatic  #CP                 // Method org/ek9/lang/String._of:(Ljava/lang/String;)Lorg/ek9/lang/String;
       119: astore        18
       121: aload         17
       123: aload         18
       125: invokevirtual #CP                 // Method org/ek9/lang/Stdout.println:(Lorg/ek9/lang/String;)V
       128: bipush        10
       130: invokestatic  #CP                 // Method java/lang/Integer.toString:(I)Ljava/lang/String;
       133: invokestatic  #CP                 // Method org/ek9/lang/Integer._of:(Ljava/lang/String;)Lorg/ek9/lang/Integer;
       136: astore        19
       138: aload         19
       140: astore        5
       142: goto          181
       145: aload_3
       146: astore        20
       148: ldc           #CP                 // String Threshold:
       150: invokestatic  #CP                 // Method org/ek9/lang/String._of:(Ljava/lang/String;)Lorg/ek9/lang/String;
       153: astore        21
       155: aload_1
       156: astore        22
       158: aload         22
       160: invokevirtual #CP                 // Method org/ek9/lang/Integer._string:()Lorg/ek9/lang/String;
       163: astore        23
       165: aload         21
       167: aload         23
       169: invokevirtual #CP                 // Method org/ek9/lang/String._add:(Lorg/ek9/lang/String;)Lorg/ek9/lang/String;
       172: astore        24
       174: aload         20
       176: aload         24
       178: invokevirtual #CP                 // Method org/ek9/lang/Stdout.println:(Lorg/ek9/lang/String;)V
       181: aconst_null
       182: astore        25
       184: aload_2
       185: astore        26
       187: aload         26
       189: astore        25
       191: aload_2
       192: astore        27
       194: iconst_1
       195: invokestatic  #CP                 // Method java/lang/Integer.toString:(I)Ljava/lang/String;
       198: invokestatic  #CP                 // Method org/ek9/lang/Integer._of:(Ljava/lang/String;)Lorg/ek9/lang/Integer;
       201: astore        28
       203: aload         27
       205: aload         28
       207: invokevirtual #CP                 // Method org/ek9/lang/Integer._lt:(Lorg/ek9/lang/Integer;)Lorg/ek9/lang/Boolean;
       210: astore        29
       212: aload         29
       214: invokevirtual #CP                 // Method org/ek9/lang/Boolean._true:()Z
       217: istore        30
       219: iload         30
       221: ifne          262
       224: aload_2
       225: astore        31
       227: bipush        20
       229: invokestatic  #CP                 // Method java/lang/Integer.toString:(I)Ljava/lang/String;
       232: invokestatic  #CP                 // Method org/ek9/lang/Integer._of:(Ljava/lang/String;)Lorg/ek9/lang/Integer;
       235: astore        32
       237: aload         31
       239: aload         32
       241: invokevirtual #CP                 // Method org/ek9/lang/Integer._gt:(Lorg/ek9/lang/Integer;)Lorg/ek9/lang/Boolean;
       244: astore        33
       246: aload         29
       248: aload         33
       250: invokevirtual #CP                 // Method org/ek9/lang/Boolean._or:(Lorg/ek9/lang/Boolean;)Lorg/ek9/lang/Boolean;
       253: astore        34
       255: aload         34
       257: astore        35
       259: goto          266
       262: aload         29
       264: astore        35
       266: aload         35
       268: invokevirtual #CP                 // Method org/ek9/lang/Boolean._true:()Z
       271: istore        36
       273: iload         36
       275: ifeq          311
       278: aload_3
       279: astore        37
       281: ldc           #CP                 // String Iterations out of range, using 5
       283: invokestatic  #CP                 // Method org/ek9/lang/String._of:(Ljava/lang/String;)Lorg/ek9/lang/String;
       286: astore        38
       288: aload         37
       290: aload         38
       292: invokevirtual #CP                 // Method org/ek9/lang/Stdout.println:(Lorg/ek9/lang/String;)V
       295: iconst_5
       296: invokestatic  #CP                 // Method java/lang/Integer.toString:(I)Ljava/lang/String;
       299: invokestatic  #CP                 // Method org/ek9/lang/Integer._of:(Ljava/lang/String;)Lorg/ek9/lang/Integer;
       302: astore        39
       304: aload         39
       306: astore        25
       308: goto          347
       311: aload_3
       312: astore        40
       314: ldc           #CP                 // String Iterations:
       316: invokestatic  #CP                 // Method org/ek9/lang/String._of:(Ljava/lang/String;)Lorg/ek9/lang/String;
       319: astore        41
       321: aload_2
       322: astore        42
       324: aload         42
       326: invokevirtual #CP                 // Method org/ek9/lang/Integer._string:()Lorg/ek9/lang/String;
       329: astore        43
       331: aload         41
       333: aload         43
       335: invokevirtual #CP                 // Method org/ek9/lang/String._add:(Lorg/ek9/lang/String;)Lorg/ek9/lang/String;
       338: astore        44
       340: aload         40
       342: aload         44
       344: invokevirtual #CP                 // Method org/ek9/lang/Stdout.println:(Lorg/ek9/lang/String;)V
       347: aconst_null
       348: astore        45
       350: iconst_0
       351: invokestatic  #CP                 // Method java/lang/Integer.toString:(I)Ljava/lang/String;
       354: invokestatic  #CP                 // Method org/ek9/lang/Integer._of:(Ljava/lang/String;)Lorg/ek9/lang/Integer;
       357: astore        46
       359: aload         46
       361: astore        45
       363: aconst_null
       364: astore        47
       366: iconst_0
       367: invokestatic  #CP                 // Method java/lang/Integer.toString:(I)Ljava/lang/String;
       370: invokestatic  #CP                 // Method org/ek9/lang/Integer._of:(Ljava/lang/String;)Lorg/ek9/lang/Integer;
       373: astore        48
       375: aload         48
       377: astore        47
       379: aload         45
       381: astore        49
       383: aload         25
       385: astore        50
       387: aload         49
       389: aload         50
       391: invokevirtual #CP                 // Method org/ek9/lang/Integer._lt:(Lorg/ek9/lang/Integer;)Lorg/ek9/lang/Boolean;
       394: astore        51
       396: aload         51
       398: invokevirtual #CP                 // Method org/ek9/lang/Boolean._true:()Z
       401: istore        52
       403: iload         52
       405: ifeq          1944
       408: aload_3
       409: astore        53
       411: ldc           #CP                 // String === Iteration
       413: invokestatic  #CP                 // Method org/ek9/lang/String._of:(Ljava/lang/String;)Lorg/ek9/lang/String;
       416: astore        54
       418: aload         45
       420: astore        55
       422: aload         55
       424: invokevirtual #CP                 // Method org/ek9/lang/Integer._string:()Lorg/ek9/lang/String;
       427: astore        56
       429: aload         54
       431: aload         56
       433: invokevirtual #CP                 // Method org/ek9/lang/String._add:(Lorg/ek9/lang/String;)Lorg/ek9/lang/String;
       436: astore        57
       438: ldc           #CP                 // String  ===
       440: invokestatic  #CP                 // Method org/ek9/lang/String._of:(Ljava/lang/String;)Lorg/ek9/lang/String;
       443: astore        58
       445: aload         57
       447: aload         58
       449: invokevirtual #CP                 // Method org/ek9/lang/String._add:(Lorg/ek9/lang/String;)Lorg/ek9/lang/String;
       452: astore        59
       454: aload         53
       456: aload         59
       458: invokevirtual #CP                 // Method org/ek9/lang/Stdout.println:(Lorg/ek9/lang/String;)V
       461: aconst_null
       462: astore        60
       464: iconst_0
       465: invokestatic  #CP                 // Method java/lang/Integer.toString:(I)Ljava/lang/String;
       468: invokestatic  #CP                 // Method org/ek9/lang/Integer._of:(Ljava/lang/String;)Lorg/ek9/lang/Integer;
       471: astore        61
       473: aload         61
       475: astore        60
       477: aload         45
       479: astore        62
       481: iconst_2
       482: invokestatic  #CP                 // Method java/lang/Integer.toString:(I)Ljava/lang/String;
       485: invokestatic  #CP                 // Method org/ek9/lang/Integer._of:(Ljava/lang/String;)Lorg/ek9/lang/Integer;
       488: astore        63
       490: aload         62
       492: aload         63
       494: invokevirtual #CP                 // Method org/ek9/lang/Integer._mod:(Lorg/ek9/lang/Integer;)Lorg/ek9/lang/Integer;
       497: astore        64
       499: iconst_0
       500: invokestatic  #CP                 // Method java/lang/Integer.toString:(I)Ljava/lang/String;
       503: invokestatic  #CP                 // Method org/ek9/lang/Integer._of:(Ljava/lang/String;)Lorg/ek9/lang/Integer;
       506: astore        65
       508: aload         64
       510: aload         65
       512: invokevirtual #CP                 // Method org/ek9/lang/Integer._eq:(Lorg/ek9/lang/Integer;)Lorg/ek9/lang/Boolean;
       515: astore        66
       517: aload         66
       519: invokevirtual #CP                 // Method org/ek9/lang/Boolean._true:()Z
       522: istore        67
       524: iload         67
       526: ifeq          1149
       529: aload_3
       530: astore        68
       532: ldc           #CP                 // String Even iteration - using for-range
       534: invokestatic  #CP                 // Method org/ek9/lang/String._of:(Ljava/lang/String;)Lorg/ek9/lang/String;
       537: astore        69
       539: aload         68
       541: aload         69
       543: invokevirtual #CP                 // Method org/ek9/lang/Stdout.println:(Lorg/ek9/lang/String;)V
       546: aconst_null
       547: astore        70
       549: iconst_1
       550: invokestatic  #CP                 // Method java/lang/Integer.toString:(I)Ljava/lang/String;
       553: invokestatic  #CP                 // Method org/ek9/lang/Integer._of:(Ljava/lang/String;)Lorg/ek9/lang/Integer;
       556: astore        71
       558: aload         71
       560: astore        72
       562: aload         5
       564: astore        73
       566: aload         73
       568: astore        74
       570: aload         72
       572: invokevirtual #CP                 // Method org/ek9/lang/Integer._isSet:()Lorg/ek9/lang/Boolean;
       575: astore        75
       577: aload         75
       579: invokevirtual #CP                 // Method org/ek9/lang/Boolean._true:()Z
       582: istore        76
       584: iload         76
       586: ifne          599
       589: new           #CP                 // class java/lang/AssertionError
       592: dup
       593: ldc           #CP                 // String For-range \'start\' value must be set
       595: invokespecial #CP                 // Method java/lang/AssertionError."<init>":(Ljava/lang/Object;)V
       598: athrow
       599: aload         74
       601: invokevirtual #CP                 // Method org/ek9/lang/Integer._isSet:()Lorg/ek9/lang/Boolean;
       604: astore        77
       606: aload         77
       608: invokevirtual #CP                 // Method org/ek9/lang/Boolean._true:()Z
       611: istore        78
       613: iload         78
       615: ifne          628
       618: new           #CP                 // class java/lang/AssertionError
       621: dup
       622: ldc           #CP                 // String For-range \'end\' value must be set
       624: invokespecial #CP                 // Method java/lang/AssertionError."<init>":(Ljava/lang/Object;)V
       627: athrow
       628: aload         72
       630: aload         74
       632: invokevirtual #CP                // Method org/ek9/lang/Integer._cmp:(Lorg/ek9/lang/Integer;)Lorg/ek9/lang/Integer;
       635: astore        79
       637: aload         72
       639: astore        80
       641: iconst_0
       642: invokestatic  #CP                 // Method java/lang/Integer.toString:(I)Ljava/lang/String;
       645: invokestatic  #CP                 // Method org/ek9/lang/Integer._of:(Ljava/lang/String;)Lorg/ek9/lang/Integer;
       648: astore        81
       650: aload         79
       652: aload         81
       654: invokevirtual #CP                 // Method org/ek9/lang/Integer._lt:(Lorg/ek9/lang/Integer;)Lorg/ek9/lang/Boolean;
       657: astore        82
       659: aload         82
       661: invokevirtual #CP                 // Method org/ek9/lang/Boolean._true:()Z
       664: istore        83
       666: iload         83
       668: ifne          835
       671: iconst_0
       672: invokestatic  #CP                 // Method java/lang/Integer.toString:(I)Ljava/lang/String;
       675: invokestatic  #CP                 // Method org/ek9/lang/Integer._of:(Ljava/lang/String;)Lorg/ek9/lang/Integer;
       678: astore        84
       680: aload         79
       682: aload         84
       684: invokevirtual #CP                 // Method org/ek9/lang/Integer._gt:(Lorg/ek9/lang/Integer;)Lorg/ek9/lang/Boolean;
       687: astore        85
       689: aload         85
       691: invokevirtual #CP                 // Method org/ek9/lang/Boolean._true:()Z
       694: istore        86
       696: iload         86
       698: ifne          992
       701: iconst_0
       702: invokestatic  #CP                 // Method java/lang/Integer.toString:(I)Ljava/lang/String;
       705: invokestatic  #CP                 // Method org/ek9/lang/Integer._of:(Ljava/lang/String;)Lorg/ek9/lang/Integer;
       708: astore        87
       710: aload         79
       712: aload         87
       714: invokevirtual #CP                 // Method org/ek9/lang/Integer._eq:(Lorg/ek9/lang/Integer;)Lorg/ek9/lang/Boolean;
       717: astore        88
       719: aload         88
       721: invokevirtual #CP                 // Method org/ek9/lang/Boolean._true:()Z
       724: istore        89
       726: iload         89
       728: ifeq          1146
       731: aload         80
       733: astore        70
       735: aload         60
       737: astore        90
       739: aload         70
       741: astore        91
       743: aload         90
       745: aload         91
       747: invokevirtual #CP                // Method org/ek9/lang/Integer._add:(Lorg/ek9/lang/Integer;)Lorg/ek9/lang/Integer;
       750: astore        92
       752: aload         92
       754: astore        60
       756: aload         70
       758: astore        93
       760: aload         5
       762: astore        94
       764: iconst_2
       765: invokestatic  #CP                 // Method java/lang/Integer.toString:(I)Ljava/lang/String;
       768: invokestatic  #CP                 // Method org/ek9/lang/Integer._of:(Ljava/lang/String;)Lorg/ek9/lang/Integer;
       771: astore        95
       773: aload         94
       775: aload         95
       777: invokevirtual #CP                // Method org/ek9/lang/Integer._div:(Lorg/ek9/lang/Integer;)Lorg/ek9/lang/Integer;
       780: astore        96
       782: aload         93
       784: aload         96
       786: invokevirtual #CP                 // Method org/ek9/lang/Integer._gt:(Lorg/ek9/lang/Integer;)Lorg/ek9/lang/Boolean;
       789: astore        97
       791: aload         97
       793: invokevirtual #CP                 // Method org/ek9/lang/Boolean._true:()Z
       796: istore        98
       798: iload         98
       800: ifeq          832
       803: aload         60
       805: astore        99
       807: iconst_1
       808: invokestatic  #CP                 // Method java/lang/Integer.toString:(I)Ljava/lang/String;
       811: invokestatic  #CP                 // Method org/ek9/lang/Integer._of:(Ljava/lang/String;)Lorg/ek9/lang/Integer;
       814: astore        100
       816: aload         99
       818: aload         100
       820: invokevirtual #CP                // Method org/ek9/lang/Integer._add:(Lorg/ek9/lang/Integer;)Lorg/ek9/lang/Integer;
       823: astore        101
       825: aload         101
       827: astore        60
       829: goto          832
       832: goto          1146
       835: aload         80
       837: aload         74
       839: invokevirtual #CP                // Method org/ek9/lang/Integer._cmp:(Lorg/ek9/lang/Integer;)Lorg/ek9/lang/Integer;
       842: astore        102
       844: iconst_0
       845: invokestatic  #CP                 // Method java/lang/Integer.toString:(I)Ljava/lang/String;
       848: invokestatic  #CP                 // Method org/ek9/lang/Integer._of:(Ljava/lang/String;)Lorg/ek9/lang/Integer;
       851: astore        103
       853: aload         102
       855: aload         103
       857: invokevirtual #CP                // Method org/ek9/lang/Integer._lteq:(Lorg/ek9/lang/Integer;)Lorg/ek9/lang/Boolean;
       860: astore        104
       862: aload         104
       864: invokevirtual #CP                 // Method org/ek9/lang/Boolean._true:()Z
       867: istore        105
       869: iload         105
       871: ifeq          1146
       874: aload         80
       876: astore        70
       878: aload         60
       880: astore        90
       882: aload         70
       884: astore        91
       886: aload         90
       888: aload         91
       890: invokevirtual #CP                // Method org/ek9/lang/Integer._add:(Lorg/ek9/lang/Integer;)Lorg/ek9/lang/Integer;
       893: astore        92
       895: aload         92
       897: astore        60
       899: aload         70
       901: astore        93
       903: aload         5
       905: astore        94
       907: iconst_2
       908: invokestatic  #CP                 // Method java/lang/Integer.toString:(I)Ljava/lang/String;
       911: invokestatic  #CP                 // Method org/ek9/lang/Integer._of:(Ljava/lang/String;)Lorg/ek9/lang/Integer;
       914: astore        95
       916: aload         94
       918: aload         95
       920: invokevirtual #CP                // Method org/ek9/lang/Integer._div:(Lorg/ek9/lang/Integer;)Lorg/ek9/lang/Integer;
       923: astore        96
       925: aload         93
       927: aload         96
       929: invokevirtual #CP                 // Method org/ek9/lang/Integer._gt:(Lorg/ek9/lang/Integer;)Lorg/ek9/lang/Boolean;
       932: astore        97
       934: aload         97
       936: invokevirtual #CP                 // Method org/ek9/lang/Boolean._true:()Z
       939: istore        98
       941: iload         98
       943: ifeq          975
       946: aload         60
       948: astore        99
       950: iconst_1
       951: invokestatic  #CP                 // Method java/lang/Integer.toString:(I)Ljava/lang/String;
       954: invokestatic  #CP                 // Method org/ek9/lang/Integer._of:(Ljava/lang/String;)Lorg/ek9/lang/Integer;
       957: astore        100
       959: aload         99
       961: aload         100
       963: invokevirtual #CP                // Method org/ek9/lang/Integer._add:(Lorg/ek9/lang/Integer;)Lorg/ek9/lang/Integer;
       966: astore        101
       968: aload         101
       970: astore        60
       972: goto          975
       975: aload         80
       977: invokevirtual #CP                // Method org/ek9/lang/Integer._inc:()Lorg/ek9/lang/Integer;
       980: astore        106
       982: aload         106
       984: astore        80
       986: goto          835
       989: nop
       990: nop
       991: athrow
       992: aload         80
       994: aload         74
       996: invokevirtual #CP                // Method org/ek9/lang/Integer._cmp:(Lorg/ek9/lang/Integer;)Lorg/ek9/lang/Integer;
       999: astore        107
      1001: iconst_0
      1002: invokestatic  #CP                 // Method java/lang/Integer.toString:(I)Ljava/lang/String;
      1005: invokestatic  #CP                 // Method org/ek9/lang/Integer._of:(Ljava/lang/String;)Lorg/ek9/lang/Integer;
      1008: astore        108
      1010: aload         107
      1012: aload         108
      1014: invokevirtual #CP                // Method org/ek9/lang/Integer._gteq:(Lorg/ek9/lang/Integer;)Lorg/ek9/lang/Boolean;
      1017: astore        109
      1019: aload         109
      1021: invokevirtual #CP                 // Method org/ek9/lang/Boolean._true:()Z
      1024: istore        110
      1026: iload         110
      1028: ifeq          1146
      1031: aload         80
      1033: astore        70
      1035: aload         60
      1037: astore        90
      1039: aload         70
      1041: astore        91
      1043: aload         90
      1045: aload         91
      1047: invokevirtual #CP                // Method org/ek9/lang/Integer._add:(Lorg/ek9/lang/Integer;)Lorg/ek9/lang/Integer;
      1050: astore        92
      1052: aload         92
      1054: astore        60
      1056: aload         70
      1058: astore        93
      1060: aload         5
      1062: astore        94
      1064: iconst_2
      1065: invokestatic  #CP                 // Method java/lang/Integer.toString:(I)Ljava/lang/String;
      1068: invokestatic  #CP                 // Method org/ek9/lang/Integer._of:(Ljava/lang/String;)Lorg/ek9/lang/Integer;
      1071: astore        95
      1073: aload         94
      1075: aload         95
      1077: invokevirtual #CP                // Method org/ek9/lang/Integer._div:(Lorg/ek9/lang/Integer;)Lorg/ek9/lang/Integer;
      1080: astore        96
      1082: aload         93
      1084: aload         96
      1086: invokevirtual #CP                 // Method org/ek9/lang/Integer._gt:(Lorg/ek9/lang/Integer;)Lorg/ek9/lang/Boolean;
      1089: astore        97
      1091: aload         97
      1093: invokevirtual #CP                 // Method org/ek9/lang/Boolean._true:()Z
      1096: istore        98
      1098: iload         98
      1100: ifeq          1132
      1103: aload         60
      1105: astore        99
      1107: iconst_1
      1108: invokestatic  #CP                 // Method java/lang/Integer.toString:(I)Ljava/lang/String;
      1111: invokestatic  #CP                 // Method org/ek9/lang/Integer._of:(Ljava/lang/String;)Lorg/ek9/lang/Integer;
      1114: astore        100
      1116: aload         99
      1118: aload         100
      1120: invokevirtual #CP                // Method org/ek9/lang/Integer._add:(Lorg/ek9/lang/Integer;)Lorg/ek9/lang/Integer;
      1123: astore        101
      1125: aload         101
      1127: astore        60
      1129: goto          1132
      1132: aload         80
      1134: invokevirtual #CP                // Method org/ek9/lang/Integer._dec:()Lorg/ek9/lang/Integer;
      1137: astore        111
      1139: aload         111
      1141: astore        80
      1143: goto          992
      1146: goto          1857
      1149: aload_3
      1150: astore        112
      1152: ldc           #CP                // String Odd iteration - using switch
      1154: invokestatic  #CP                 // Method org/ek9/lang/String._of:(Ljava/lang/String;)Lorg/ek9/lang/String;
      1157: astore        113
      1159: aload         112
      1161: aload         113
      1163: invokevirtual #CP                 // Method org/ek9/lang/Stdout.println:(Lorg/ek9/lang/String;)V
      1166: aload         45
      1168: astore        114
      1170: aload         114
      1172: astore        115
      1174: iconst_1
      1175: invokestatic  #CP                 // Method java/lang/Integer.toString:(I)Ljava/lang/String;
      1178: invokestatic  #CP                 // Method org/ek9/lang/Integer._of:(Ljava/lang/String;)Lorg/ek9/lang/Integer;
      1181: astore        116
      1183: aload         115
      1185: aload         116
      1187: invokevirtual #CP                 // Method org/ek9/lang/Integer._eq:(Lorg/ek9/lang/Integer;)Lorg/ek9/lang/Boolean;
      1190: astore        117
      1192: aload         117
      1194: invokevirtual #CP                 // Method org/ek9/lang/Boolean._true:()Z
      1197: istore        118
      1199: iload         118
      1201: ifeq          1321
      1204: aload_3
      1205: astore        119
      1207: ldc           #CP                // String Case 1: do-while loop
      1209: invokestatic  #CP                 // Method org/ek9/lang/String._of:(Ljava/lang/String;)Lorg/ek9/lang/String;
      1212: astore        120
      1214: aload         119
      1216: aload         120
      1218: invokevirtual #CP                 // Method org/ek9/lang/Stdout.println:(Lorg/ek9/lang/String;)V
      1221: aconst_null
      1222: astore        121
      1224: iconst_1
      1225: invokestatic  #CP                 // Method java/lang/Integer.toString:(I)Ljava/lang/String;
      1228: invokestatic  #CP                 // Method org/ek9/lang/Integer._of:(Ljava/lang/String;)Lorg/ek9/lang/Integer;
      1231: astore        122
      1233: aload         122
      1235: astore        121
      1237: aload         60
      1239: astore        123
      1241: aload         121
      1243: astore        124
      1245: aload         123
      1247: aload         124
      1249: invokevirtual #CP                // Method org/ek9/lang/Integer._add:(Lorg/ek9/lang/Integer;)Lorg/ek9/lang/Integer;
      1252: astore        125
      1254: aload         125
      1256: astore        60
      1258: aload         121
      1260: astore        126
      1262: iconst_1
      1263: invokestatic  #CP                 // Method java/lang/Integer.toString:(I)Ljava/lang/String;
      1266: invokestatic  #CP                 // Method org/ek9/lang/Integer._of:(Ljava/lang/String;)Lorg/ek9/lang/Integer;
      1269: astore        127
      1271: aload         126
      1273: aload         127
      1275: invokevirtual #CP                // Method org/ek9/lang/Integer._add:(Lorg/ek9/lang/Integer;)Lorg/ek9/lang/Integer;
      1278: astore        128
      1280: aload         128
      1282: astore        121
      1284: aload         121
      1286: astore        129
      1288: iconst_4
      1289: invokestatic  #CP                 // Method java/lang/Integer.toString:(I)Ljava/lang/String;
      1292: invokestatic  #CP                 // Method org/ek9/lang/Integer._of:(Ljava/lang/String;)Lorg/ek9/lang/Integer;
      1295: astore        130
      1297: aload         129
      1299: aload         130
      1301: invokevirtual #CP                 // Method org/ek9/lang/Integer._lt:(Lorg/ek9/lang/Integer;)Lorg/ek9/lang/Boolean;
      1304: astore        131
      1306: aload         131
      1308: invokevirtual #CP                 // Method org/ek9/lang/Boolean._true:()Z
      1311: istore        132
      1313: iload         132
      1315: ifne          1237
      1318: goto          1857
      1321: aload         114
      1323: astore        133
      1325: iconst_3
      1326: invokestatic  #CP                 // Method java/lang/Integer.toString:(I)Ljava/lang/String;
      1329: invokestatic  #CP                 // Method org/ek9/lang/Integer._of:(Ljava/lang/String;)Lorg/ek9/lang/Integer;
      1332: astore        134
      1334: aload         133
      1336: aload         134
      1338: invokevirtual #CP                 // Method org/ek9/lang/Integer._eq:(Lorg/ek9/lang/Integer;)Lorg/ek9/lang/Boolean;
      1341: astore        135
      1343: aload         135
      1345: invokevirtual #CP                 // Method org/ek9/lang/Boolean._true:()Z
      1348: istore        136
      1350: iload         136
      1352: ifne          1400
      1355: aload         114
      1357: astore        137
      1359: iconst_5
      1360: invokestatic  #CP                 // Method java/lang/Integer.toString:(I)Ljava/lang/String;
      1363: invokestatic  #CP                 // Method org/ek9/lang/Integer._of:(Ljava/lang/String;)Lorg/ek9/lang/Integer;
      1366: astore        138
      1368: aload         137
      1370: aload         138
      1372: invokevirtual #CP                 // Method org/ek9/lang/Integer._eq:(Lorg/ek9/lang/Integer;)Lorg/ek9/lang/Boolean;
      1375: astore        139
      1377: aload         139
      1379: invokevirtual #CP                 // Method org/ek9/lang/Boolean._true:()Z
      1382: istore        140
      1384: aload         135
      1386: aload         139
      1388: invokevirtual #CP                 // Method org/ek9/lang/Boolean._or:(Lorg/ek9/lang/Boolean;)Lorg/ek9/lang/Boolean;
      1391: astore        141
      1393: aload         141
      1395: astore        141
      1397: goto          1404
      1400: aload         135
      1402: astore        141
      1404: aload         141
      1406: invokevirtual #CP                 // Method org/ek9/lang/Boolean._true:()Z
      1409: istore        142
      1411: iload         142
      1413: ifeq          1813
      1416: aload_3
      1417: astore        143
      1419: ldc           #CP                // String Case 3 or 5: for-range loop
      1421: invokestatic  #CP                 // Method org/ek9/lang/String._of:(Ljava/lang/String;)Lorg/ek9/lang/String;
      1424: astore        144
      1426: aload         143
      1428: aload         144
      1430: invokevirtual #CP                 // Method org/ek9/lang/Stdout.println:(Lorg/ek9/lang/String;)V
      1433: aconst_null
      1434: astore        145
      1436: iconst_1
      1437: invokestatic  #CP                 // Method java/lang/Integer.toString:(I)Ljava/lang/String;
      1440: invokestatic  #CP                 // Method org/ek9/lang/Integer._of:(Ljava/lang/String;)Lorg/ek9/lang/Integer;
      1443: astore        146
      1445: aload         146
      1447: astore        147
      1449: iconst_5
      1450: invokestatic  #CP                 // Method java/lang/Integer.toString:(I)Ljava/lang/String;
      1453: invokestatic  #CP                 // Method org/ek9/lang/Integer._of:(Ljava/lang/String;)Lorg/ek9/lang/Integer;
      1456: astore        148
      1458: aload         148
      1460: astore        149
      1462: aload         147
      1464: invokevirtual #CP                 // Method org/ek9/lang/Integer._isSet:()Lorg/ek9/lang/Boolean;
      1467: astore        150
      1469: aload         150
      1471: invokevirtual #CP                 // Method org/ek9/lang/Boolean._true:()Z
      1474: istore        151
      1476: iload         151
      1478: ifne          1491
      1481: new           #CP                 // class java/lang/AssertionError
      1484: dup
      1485: ldc           #CP                 // String For-range \'start\' value must be set
      1487: invokespecial #CP                 // Method java/lang/AssertionError."<init>":(Ljava/lang/Object;)V
      1490: athrow
      1491: aload         149
      1493: invokevirtual #CP                 // Method org/ek9/lang/Integer._isSet:()Lorg/ek9/lang/Boolean;
      1496: astore        152
      1498: aload         152
      1500: invokevirtual #CP                 // Method org/ek9/lang/Boolean._true:()Z
      1503: istore        153
      1505: iload         153
      1507: ifne          1520
      1510: new           #CP                 // class java/lang/AssertionError
      1513: dup
      1514: ldc           #CP                 // String For-range \'end\' value must be set
      1516: invokespecial #CP                 // Method java/lang/AssertionError."<init>":(Ljava/lang/Object;)V
      1519: athrow
      1520: aload         147
      1522: aload         149
      1524: invokevirtual #CP                // Method org/ek9/lang/Integer._cmp:(Lorg/ek9/lang/Integer;)Lorg/ek9/lang/Integer;
      1527: astore        154
      1529: aload         147
      1531: astore        155
      1533: iconst_0
      1534: invokestatic  #CP                 // Method java/lang/Integer.toString:(I)Ljava/lang/String;
      1537: invokestatic  #CP                 // Method org/ek9/lang/Integer._of:(Ljava/lang/String;)Lorg/ek9/lang/Integer;
      1540: astore        156
      1542: aload         154
      1544: aload         156
      1546: invokevirtual #CP                 // Method org/ek9/lang/Integer._lt:(Lorg/ek9/lang/Integer;)Lorg/ek9/lang/Boolean;
      1549: astore        157
      1551: aload         157
      1553: invokevirtual #CP                 // Method org/ek9/lang/Boolean._true:()Z
      1556: istore        158
      1558: iload         158
      1560: ifne          1651
      1563: iconst_0
      1564: invokestatic  #CP                 // Method java/lang/Integer.toString:(I)Ljava/lang/String;
      1567: invokestatic  #CP                 // Method org/ek9/lang/Integer._of:(Ljava/lang/String;)Lorg/ek9/lang/Integer;
      1570: astore        159
      1572: aload         154
      1574: aload         159
      1576: invokevirtual #CP                 // Method org/ek9/lang/Integer._gt:(Lorg/ek9/lang/Integer;)Lorg/ek9/lang/Boolean;
      1579: astore        160
      1581: aload         160
      1583: invokevirtual #CP                 // Method org/ek9/lang/Boolean._true:()Z
      1586: istore        161
      1588: iload         161
      1590: ifne          1732
      1593: iconst_0
      1594: invokestatic  #CP                 // Method java/lang/Integer.toString:(I)Ljava/lang/String;
      1597: invokestatic  #CP                 // Method org/ek9/lang/Integer._of:(Ljava/lang/String;)Lorg/ek9/lang/Integer;
      1600: astore        162
      1602: aload         154
      1604: aload         162
      1606: invokevirtual #CP                 // Method org/ek9/lang/Integer._eq:(Lorg/ek9/lang/Integer;)Lorg/ek9/lang/Boolean;
      1609: astore        163
      1611: aload         163
      1613: invokevirtual #CP                 // Method org/ek9/lang/Boolean._true:()Z
      1616: istore        164
      1618: iload         164
      1620: ifeq          1810
      1623: aload         155
      1625: astore        145
      1627: aload         60
      1629: astore        165
      1631: aload         145
      1633: astore        166
      1635: aload         165
      1637: aload         166
      1639: invokevirtual #CP                // Method org/ek9/lang/Integer._add:(Lorg/ek9/lang/Integer;)Lorg/ek9/lang/Integer;
      1642: astore        167
      1644: aload         167
      1646: astore        60
      1648: goto          1810
      1651: aload         155
      1653: aload         149
      1655: invokevirtual #CP                // Method org/ek9/lang/Integer._cmp:(Lorg/ek9/lang/Integer;)Lorg/ek9/lang/Integer;
      1658: astore        168
      1660: iconst_0
      1661: invokestatic  #CP                 // Method java/lang/Integer.toString:(I)Ljava/lang/String;
      1664: invokestatic  #CP                 // Method org/ek9/lang/Integer._of:(Ljava/lang/String;)Lorg/ek9/lang/Integer;
      1667: astore        169
      1669: aload         168
      1671: aload         169
      1673: invokevirtual #CP                // Method org/ek9/lang/Integer._lteq:(Lorg/ek9/lang/Integer;)Lorg/ek9/lang/Boolean;
      1676: astore        170
      1678: aload         170
      1680: invokevirtual #CP                 // Method org/ek9/lang/Boolean._true:()Z
      1683: istore        171
      1685: iload         171
      1687: ifeq          1810
      1690: aload         155
      1692: astore        145
      1694: aload         60
      1696: astore        165
      1698: aload         145
      1700: astore        166
      1702: aload         165
      1704: aload         166
      1706: invokevirtual #CP                // Method org/ek9/lang/Integer._add:(Lorg/ek9/lang/Integer;)Lorg/ek9/lang/Integer;
      1709: astore        167
      1711: aload         167
      1713: astore        60
      1715: aload         155
      1717: invokevirtual #CP                // Method org/ek9/lang/Integer._inc:()Lorg/ek9/lang/Integer;
      1720: astore        172
      1722: aload         172
      1724: astore        155
      1726: goto          1651
      1729: nop
      1730: nop
      1731: athrow
      1732: aload         155
      1734: aload         149
      1736: invokevirtual #CP                // Method org/ek9/lang/Integer._cmp:(Lorg/ek9/lang/Integer;)Lorg/ek9/lang/Integer;
      1739: astore        173
      1741: iconst_0
      1742: invokestatic  #CP                 // Method java/lang/Integer.toString:(I)Ljava/lang/String;
      1745: invokestatic  #CP                 // Method org/ek9/lang/Integer._of:(Ljava/lang/String;)Lorg/ek9/lang/Integer;
      1748: astore        174
      1750: aload         173
      1752: aload         174
      1754: invokevirtual #CP                // Method org/ek9/lang/Integer._gteq:(Lorg/ek9/lang/Integer;)Lorg/ek9/lang/Boolean;
      1757: astore        175
      1759: aload         175
      1761: invokevirtual #CP                 // Method org/ek9/lang/Boolean._true:()Z
      1764: istore        176
      1766: iload         176
      1768: ifeq          1810
      1771: aload         155
      1773: astore        145
      1775: aload         60
      1777: astore        165
      1779: aload         145
      1781: astore        166
      1783: aload         165
      1785: aload         166
      1787: invokevirtual #CP                // Method org/ek9/lang/Integer._add:(Lorg/ek9/lang/Integer;)Lorg/ek9/lang/Integer;
      1790: astore        167
      1792: aload         167
      1794: astore        60
      1796: aload         155
      1798: invokevirtual #CP                // Method org/ek9/lang/Integer._dec:()Lorg/ek9/lang/Integer;
      1801: astore        177
      1803: aload         177
      1805: astore        155
      1807: goto          1732
      1810: goto          1857
      1813: aload_3
      1814: astore        178
      1816: ldc           #CP                // String Default case: simple computation
      1818: invokestatic  #CP                 // Method org/ek9/lang/String._of:(Ljava/lang/String;)Lorg/ek9/lang/String;
      1821: astore        179
      1823: aload         178
      1825: aload         179
      1827: invokevirtual #CP                 // Method org/ek9/lang/Stdout.println:(Lorg/ek9/lang/String;)V
      1830: aload         45
      1832: astore        180
      1834: bipush        10
      1836: invokestatic  #CP                 // Method java/lang/Integer.toString:(I)Ljava/lang/String;
      1839: invokestatic  #CP                 // Method org/ek9/lang/Integer._of:(Ljava/lang/String;)Lorg/ek9/lang/Integer;
      1842: astore        181
      1844: aload         180
      1846: aload         181
      1848: invokevirtual #CP                // Method org/ek9/lang/Integer._mul:(Lorg/ek9/lang/Integer;)Lorg/ek9/lang/Integer;
      1851: astore        182
      1853: aload         182
      1855: astore        60
      1857: aload_3
      1858: astore        183
      1860: ldc           #CP                // String Iteration result:
      1862: invokestatic  #CP                 // Method org/ek9/lang/String._of:(Ljava/lang/String;)Lorg/ek9/lang/String;
      1865: astore        184
      1867: aload         60
      1869: astore        185
      1871: aload         185
      1873: invokevirtual #CP                 // Method org/ek9/lang/Integer._string:()Lorg/ek9/lang/String;
      1876: astore        186
      1878: aload         184
      1880: aload         186
      1882: invokevirtual #CP                 // Method org/ek9/lang/String._add:(Lorg/ek9/lang/String;)Lorg/ek9/lang/String;
      1885: astore        187
      1887: aload         183
      1889: aload         187
      1891: invokevirtual #CP                 // Method org/ek9/lang/Stdout.println:(Lorg/ek9/lang/String;)V
      1894: aload         47
      1896: astore        188
      1898: aload         60
      1900: astore        189
      1902: aload         188
      1904: aload         189
      1906: invokevirtual #CP                // Method org/ek9/lang/Integer._add:(Lorg/ek9/lang/Integer;)Lorg/ek9/lang/Integer;
      1909: astore        190
      1911: aload         190
      1913: astore        47
      1915: aload         45
      1917: astore        191
      1919: iconst_1
      1920: invokestatic  #CP                 // Method java/lang/Integer.toString:(I)Ljava/lang/String;
      1923: invokestatic  #CP                 // Method org/ek9/lang/Integer._of:(Ljava/lang/String;)Lorg/ek9/lang/Integer;
      1926: astore        192
      1928: aload         191
      1930: aload         192
      1932: invokevirtual #CP                // Method org/ek9/lang/Integer._add:(Lorg/ek9/lang/Integer;)Lorg/ek9/lang/Integer;
      1935: astore        193
      1937: aload         193
      1939: astore        45
      1941: goto          379
      1944: aload_3
      1945: astore        194
      1947: ldc           #CP                // String === Final Results ===
      1949: invokestatic  #CP                 // Method org/ek9/lang/String._of:(Ljava/lang/String;)Lorg/ek9/lang/String;
      1952: astore        195
      1954: aload         194
      1956: aload         195
      1958: invokevirtual #CP                 // Method org/ek9/lang/Stdout.println:(Lorg/ek9/lang/String;)V
      1961: aload_3
      1962: astore        196
      1964: ldc           #CP                // String Grand total:
      1966: invokestatic  #CP                 // Method org/ek9/lang/String._of:(Ljava/lang/String;)Lorg/ek9/lang/String;
      1969: astore        197
      1971: aload         47
      1973: astore        198
      1975: aload         198
      1977: invokevirtual #CP                 // Method org/ek9/lang/Integer._string:()Lorg/ek9/lang/String;
      1980: astore        199
      1982: aload         197
      1984: aload         199
      1986: invokevirtual #CP                 // Method org/ek9/lang/String._add:(Lorg/ek9/lang/String;)Lorg/ek9/lang/String;
      1989: astore        200
      1991: aload         196
      1993: aload         200
      1995: invokevirtual #CP                 // Method org/ek9/lang/Stdout.println:(Lorg/ek9/lang/String;)V
      1998: aconst_null
      1999: astore        201
      2001: ldc           #CP                // String Unknown
      2003: invokestatic  #CP                 // Method org/ek9/lang/String._of:(Ljava/lang/String;)Lorg/ek9/lang/String;
      2006: astore        202
      2008: aload         202
      2010: astore        201
      2012: aload         47
      2014: astore        203
      2016: bipush        100
      2018: invokestatic  #CP                 // Method java/lang/Integer.toString:(I)Ljava/lang/String;
      2021: invokestatic  #CP                 // Method org/ek9/lang/Integer._of:(Ljava/lang/String;)Lorg/ek9/lang/Integer;
      2024: astore        204
      2026: aload         203
      2028: aload         204
      2030: invokevirtual #CP                 // Method org/ek9/lang/Integer._lt:(Lorg/ek9/lang/Integer;)Lorg/ek9/lang/Boolean;
      2033: astore        205
      2035: aload         205
      2037: invokevirtual #CP                 // Method org/ek9/lang/Boolean._true:()Z
      2040: istore        206
      2042: iload         206
      2044: ifeq          2061
      2047: ldc           #CP                // String Small
      2049: invokestatic  #CP                 // Method org/ek9/lang/String._of:(Ljava/lang/String;)Lorg/ek9/lang/String;
      2052: astore        207
      2054: aload         207
      2056: astore        201
      2058: goto          2172
      2061: aload         47
      2063: astore        208
      2065: sipush        500
      2068: invokestatic  #CP                 // Method java/lang/Integer.toString:(I)Ljava/lang/String;
      2071: invokestatic  #CP                 // Method org/ek9/lang/Integer._of:(Ljava/lang/String;)Lorg/ek9/lang/Integer;
      2074: astore        209
      2076: aload         208
      2078: aload         209
      2080: invokevirtual #CP                 // Method org/ek9/lang/Integer._lt:(Lorg/ek9/lang/Integer;)Lorg/ek9/lang/Boolean;
      2083: astore        210
      2085: aload         210
      2087: invokevirtual #CP                 // Method org/ek9/lang/Boolean._true:()Z
      2090: istore        211
      2092: iload         211
      2094: ifeq          2111
      2097: ldc           #CP                // String Medium
      2099: invokestatic  #CP                 // Method org/ek9/lang/String._of:(Ljava/lang/String;)Lorg/ek9/lang/String;
      2102: astore        212
      2104: aload         212
      2106: astore        201
      2108: goto          2172
      2111: aload         47
      2113: astore        213
      2115: sipush        2000
      2118: invokestatic  #CP                 // Method java/lang/Integer.toString:(I)Ljava/lang/String;
      2121: invokestatic  #CP                 // Method org/ek9/lang/Integer._of:(Ljava/lang/String;)Lorg/ek9/lang/Integer;
      2124: astore        214
      2126: aload         213
      2128: aload         214
      2130: invokevirtual #CP                 // Method org/ek9/lang/Integer._lt:(Lorg/ek9/lang/Integer;)Lorg/ek9/lang/Boolean;
      2133: astore        215
      2135: aload         215
      2137: invokevirtual #CP                 // Method org/ek9/lang/Boolean._true:()Z
      2140: istore        216
      2142: iload         216
      2144: ifeq          2161
      2147: ldc           #CP                // String Large
      2149: invokestatic  #CP                 // Method org/ek9/lang/String._of:(Ljava/lang/String;)Lorg/ek9/lang/String;
      2152: astore        217
      2154: aload         217
      2156: astore        201
      2158: goto          2172
      2161: ldc           #CP                // String Very Large
      2163: invokestatic  #CP                 // Method org/ek9/lang/String._of:(Ljava/lang/String;)Lorg/ek9/lang/String;
      2166: astore        218
      2168: aload         218
      2170: astore        201
      2172: aload_3
      2173: astore        219
      2175: ldc           #CP                // String Category:
      2177: invokestatic  #CP                 // Method org/ek9/lang/String._of:(Ljava/lang/String;)Lorg/ek9/lang/String;
      2180: astore        220
      2182: aload         201
      2184: astore        221
      2186: aload         220
      2188: aload         221
      2190: invokevirtual #CP                 // Method org/ek9/lang/String._add:(Lorg/ek9/lang/String;)Lorg/ek9/lang/String;
      2193: astore        222
      2195: aload         219
      2197: aload         222
      2199: invokevirtual #CP                 // Method org/ek9/lang/Stdout.println:(Lorg/ek9/lang/String;)V
      2202: aload         47
      2204: astore        223
      2206: sipush        200
      2209: invokestatic  #CP                 // Method java/lang/Integer.toString:(I)Ljava/lang/String;
      2212: invokestatic  #CP                 // Method org/ek9/lang/Integer._of:(Ljava/lang/String;)Lorg/ek9/lang/Integer;
      2215: astore        224
      2217: aload         223
      2219: aload         224
      2221: invokevirtual #CP                 // Method org/ek9/lang/Integer._gt:(Lorg/ek9/lang/Integer;)Lorg/ek9/lang/Boolean;
      2224: astore        225
      2226: aload         225
      2228: invokevirtual #CP                 // Method org/ek9/lang/Boolean._true:()Z
      2231: istore        226
      2233: iload         226
      2235: ifeq          2271
      2238: aload         45
      2240: astore        227
      2242: aload         25
      2244: astore        228
      2246: aload         227
      2248: aload         228
      2250: invokevirtual #CP                 // Method org/ek9/lang/Integer._eq:(Lorg/ek9/lang/Integer;)Lorg/ek9/lang/Boolean;
      2253: astore        229
      2255: aload         225
      2257: aload         229
      2259: invokevirtual #CP                // Method org/ek9/lang/Boolean._and:(Lorg/ek9/lang/Boolean;)Lorg/ek9/lang/Boolean;
      2262: astore        230
      2264: aload         230
      2266: astore        231
      2268: goto          2275
      2271: aload         225
      2273: astore        231
      2275: aload         231
      2277: invokevirtual #CP                 // Method org/ek9/lang/Boolean._true:()Z
      2280: istore        232
      2282: iload         232
      2284: ifeq          2307
      2287: aload_3
      2288: astore        233
      2290: ldc           #CP                // String Status: SUCCESS - High total with all iterations
      2292: invokestatic  #CP                 // Method org/ek9/lang/String._of:(Ljava/lang/String;)Lorg/ek9/lang/String;
      2295: astore        234
      2297: aload         233
      2299: aload         234
      2301: invokevirtual #CP                 // Method org/ek9/lang/Stdout.println:(Lorg/ek9/lang/String;)V
      2304: goto          2433
      2307: aload         47
      2309: astore        235
      2311: bipush        50
      2313: invokestatic  #CP                 // Method java/lang/Integer.toString:(I)Ljava/lang/String;
      2316: invokestatic  #CP                 // Method org/ek9/lang/Integer._of:(Ljava/lang/String;)Lorg/ek9/lang/Integer;
      2319: astore        236
      2321: aload         235
      2323: aload         236
      2325: invokevirtual #CP                 // Method org/ek9/lang/Integer._gt:(Lorg/ek9/lang/Integer;)Lorg/ek9/lang/Boolean;
      2328: astore        237
      2330: aload         237
      2332: invokevirtual #CP                 // Method org/ek9/lang/Boolean._true:()Z
      2335: istore        238
      2337: iload         238
      2339: ifne          2380
      2342: aload         45
      2344: astore        239
      2346: iconst_0
      2347: invokestatic  #CP                 // Method java/lang/Integer.toString:(I)Ljava/lang/String;
      2350: invokestatic  #CP                 // Method org/ek9/lang/Integer._of:(Ljava/lang/String;)Lorg/ek9/lang/Integer;
      2353: astore        240
      2355: aload         239
      2357: aload         240
      2359: invokevirtual #CP                 // Method org/ek9/lang/Integer._gt:(Lorg/ek9/lang/Integer;)Lorg/ek9/lang/Boolean;
      2362: astore        241
      2364: aload         237
      2366: aload         241
      2368: invokevirtual #CP                 // Method org/ek9/lang/Boolean._or:(Lorg/ek9/lang/Boolean;)Lorg/ek9/lang/Boolean;
      2371: astore        242
      2373: aload         242
      2375: astore        243
      2377: goto          2384
      2380: aload         237
      2382: astore        243
      2384: aload         243
      2386: invokevirtual #CP                 // Method org/ek9/lang/Boolean._true:()Z
      2389: istore        244
      2391: iload         244
      2393: ifeq          2416
      2396: aload_3
      2397: astore        245
      2399: ldc           #CP                // String Status: PARTIAL - Some computation completed
      2401: invokestatic  #CP                 // Method org/ek9/lang/String._of:(Ljava/lang/String;)Lorg/ek9/lang/String;
      2404: astore        246
      2406: aload         245
      2408: aload         246
      2410: invokevirtual #CP                 // Method org/ek9/lang/Stdout.println:(Lorg/ek9/lang/String;)V
      2413: goto          2433
      2416: aload_3
      2417: astore        247
      2419: ldc           #CP                // String Status: MINIMAL - Low computation
      2421: invokestatic  #CP                 // Method org/ek9/lang/String._of:(Ljava/lang/String;)Lorg/ek9/lang/String;
      2424: astore        248
      2426: aload         247
      2428: aload         248
      2430: invokevirtual #CP                 // Method org/ek9/lang/Stdout.println:(Lorg/ek9/lang/String;)V
      2433: aload_3
      2434: astore        249
      2436: ldc           #CP                // String Program complete
      2438: invokestatic  #CP                 // Method org/ek9/lang/String._of:(Ljava/lang/String;)Lorg/ek9/lang/String;
      2441: astore        250
      2443: aload         249
      2445: aload         250
      2447: invokevirtual #CP                 // Method org/ek9/lang/Stdout.println:(Lorg/ek9/lang/String;)V
      2450: return

  static {};
    Code:
         0: return

  private void i_init();
    Code:
         0: return
}`
    ComprehensiveNestedControlFlow()
      ->
        threshold as Integer
        iterations as Integer

      stdout <- Stdout()

      // Input validation with if/else and boolean OR
      validThreshold <- threshold
      if threshold < 1 or threshold > 100
        stdout.println("Threshold out of range, using 10")
        validThreshold := 10
      else
        stdout.println("Threshold: " + $threshold)

      validIterations <- iterations
      if iterations < 1 or iterations > 20
        stdout.println("Iterations out of range, using 5")
        validIterations := 5
      else
        stdout.println("Iterations: " + $iterations)

      counter <- 0
      grandTotal <- 0

      // OUTER LEVEL: while loop
      while counter < validIterations
        stdout.println("=== Iteration " + $counter + " ===")
        iterationResult <- 0

        // NESTED LEVEL 1: if/else inside while
        if counter mod 2 == 0
          stdout.println("Even iteration - using for-range")

          // NESTED LEVEL 2: for-range inside if branch
          for i in 1 ... validThreshold
            iterationResult := iterationResult + i

            // NESTED LEVEL 3: if inside for loop
            if i > validThreshold / 2
              iterationResult := iterationResult + 1

        else
          stdout.println("Odd iteration - using switch")

          // NESTED LEVEL 2: switch inside else branch
          switch counter
            case 1
              stdout.println("Case 1: do-while loop")
              // NESTED LEVEL 3: do-while inside switch case
              temp <- 1
              do
                iterationResult := iterationResult + temp
                temp := temp + 1
              while temp < 4

            case 3, 5
              stdout.println("Case 3 or 5: for-range loop")
              // NESTED LEVEL 3: for-range inside switch case
              for j in 1 ... 5
                iterationResult := iterationResult + j

            default
              stdout.println("Default case: simple computation")
              iterationResult := counter * 10

        stdout.println("Iteration result: " + $iterationResult)
        grandTotal := grandTotal + iterationResult
        counter := counter + 1

      // OUTER LEVEL: Final categorization with if/else chain
      stdout.println("=== Final Results ===")
      stdout.println("Grand total: " + $grandTotal)

      // Categorize the result
      category <- "Unknown"
      if grandTotal < 100
        category := "Small"
      else if grandTotal < 500
        category := "Medium"
      else if grandTotal < 2000
        category := "Large"
      else
        category := "Very Large"

      stdout.println("Category: " + category)

      // Complex boolean expression with AND/OR
      if grandTotal > 200 and counter == validIterations
        stdout.println("Status: SUCCESS - High total with all iterations")
      else if grandTotal > 50 or counter > 0
        stdout.println("Status: PARTIAL - Some computation completed")
      else
        stdout.println("Status: MINIMAL - Low computation")

      stdout.println("Program complete")

//EOF
