#!ek9
<?-
  Bytecode test for try-with-resources with multiple resources AND explicit finally.
  Tests the most complex scenario: resource cleanup + user finally code.

  Tests:
  - Multiple resource initialization in declaration order
  - Automatic close() calls in REVERSE order (resource2 then resource1)
  - User's explicit finally block code execution
  - Correct execution order: try → catch → implicit cleanup → explicit finally → rethrow
  - Exception table covering both resources and catch handler
-?>
defines module bytecode.test.resources.finally

  defines class

    TestResource

      TestResource()
        -> resourceName as String
        assert resourceName?

      operator close as pure
        stdout <- Stdout()
        stdout.println("Closing resource")

      override operator ? as pure
        <- rtn <- true

  defines program

    @BYTECODE: CODE_GENERATION_AGGREGATES: TYPE: "bytecode.test.resources.finally::TryWithMultipleResourcesAndFinally": `public class bytecode.test.resources.finally.TryWithMultipleResourcesAndFinally {
  public bytecode.test.resources.finally.TryWithMultipleResourcesAndFinally();
    Code:
         0: aload_0
         1: invokespecial #CP                  // Method java/lang/Object."<init>":()V
         4: aload_0
         5: invokevirtual #CP                 // Method i_init:()V
         8: return

  public void _main();
    Code:
         0: aconst_null
         1: astore_1
         2: new           #CP                 // class org/ek9/lang/String
         5: dup
         6: invokespecial #CP                 // Method org/ek9/lang/String."<init>":()V
         9: astore_2
        10: aload_2
        11: astore_1
        12: aconst_null
        13: astore_3
        14: ldc           #CP                 // String first
        16: invokestatic  #CP                 // Method org/ek9/lang/String._of:(Ljava/lang/String;)Lorg/ek9/lang/String;
        19: astore        4
        21: new           #CP                 // class bytecode/test/resources/finally/TestResource
        24: dup
        25: aload         4
        27: invokespecial #CP                 // Method bytecode/test/resources/finally/TestResource."<init>":(Lorg/ek9/lang/String;)V
        30: astore        5
        32: aload         5
        34: astore_3
        35: aconst_null
        36: astore        6
        38: ldc           #CP                 // String second
        40: invokestatic  #CP                 // Method org/ek9/lang/String._of:(Ljava/lang/String;)Lorg/ek9/lang/String;
        43: astore        7
        45: new           #CP                 // class bytecode/test/resources/finally/TestResource
        48: dup
        49: aload         7
        51: invokespecial #CP                 // Method bytecode/test/resources/finally/TestResource."<init>":(Lorg/ek9/lang/String;)V
        54: astore        8
        56: aload         8
        58: astore        6
        60: aconst_null
        61: astore        9
        63: ldc           #CP                 // String OK
        65: invokestatic  #CP                 // Method org/ek9/lang/String._of:(Ljava/lang/String;)Lorg/ek9/lang/String;
        68: astore        10
        70: aload         10
        72: astore_1
        73: aconst_null
        74: astore        11
        76: new           #CP                 // class org/ek9/lang/Stdout
        79: dup
        80: invokespecial #CP                 // Method org/ek9/lang/Stdout."<init>":()V
        83: astore        12
        85: aload         12
        87: astore        11
        89: aload         11
        91: astore        13
        93: ldc           #CP                 // String Try:
        95: invokestatic  #CP                 // Method org/ek9/lang/String._of:(Ljava/lang/String;)Lorg/ek9/lang/String;
        98: astore        14
       100: aload_1
       101: astore        15
       103: aload         14
       105: aload         15
       107: invokevirtual #CP                 // Method org/ek9/lang/String._add:(Lorg/ek9/lang/String;)Lorg/ek9/lang/String;
       110: astore        16
       112: aload         13
       114: aload         16
       116: invokevirtual #CP                 // Method org/ek9/lang/Stdout.println:(Lorg/ek9/lang/String;)V
       119: goto          143
       122: astore        17
       124: ldc           #CP                 // String ERROR
       126: invokestatic  #CP                 // Method org/ek9/lang/String._of:(Ljava/lang/String;)Lorg/ek9/lang/String;
       129: astore        18
       131: aload         18
       133: astore_1
       134: goto          143
       137: athrow
       138: astore        9
       140: goto          143
       143: new           #CP                 // class org/ek9/lang/Stdout
       146: dup
       147: invokespecial #CP                 // Method org/ek9/lang/Stdout."<init>":()V
       150: astore        19
       152: aload         19
       154: astore        11
       156: aload         11
       158: astore        20
       160: ldc           #CP                 // String Finally executed
       162: invokestatic  #CP                 // Method org/ek9/lang/String._of:(Ljava/lang/String;)Lorg/ek9/lang/String;
       165: astore        21
       167: aload         20
       169: aload         21
       171: invokevirtual #CP                 // Method org/ek9/lang/Stdout.println:(Lorg/ek9/lang/String;)V
       174: aload         6
       176: invokevirtual #CP                 // Method bytecode/test/resources/finally/TestResource._close:()V
       179: aload_3
       180: invokevirtual #CP                 // Method bytecode/test/resources/finally/TestResource._close:()V
       183: aload         9
       185: ifnull        191
       188: aload         9
       190: athrow
       191: new           #CP                 // class org/ek9/lang/Stdout
       194: dup
       195: invokespecial #CP                 // Method org/ek9/lang/Stdout."<init>":()V
       198: astore        22
       200: aload         22
       202: astore        11
       204: aload         11
       206: astore        23
       208: ldc           #CP                 // String Result:
       210: invokestatic  #CP                 // Method org/ek9/lang/String._of:(Ljava/lang/String;)Lorg/ek9/lang/String;
       213: astore        24
       215: aload_1
       216: astore        25
       218: aload         24
       220: aload         25
       222: invokevirtual #CP                 // Method org/ek9/lang/String._add:(Lorg/ek9/lang/String;)Lorg/ek9/lang/String;
       225: astore        26
       227: aload         23
       229: aload         26
       231: invokevirtual #CP                 // Method org/ek9/lang/Stdout.println:(Lorg/ek9/lang/String;)V
       234: return
      Exception table:
         from    to  target type
            63   119   122   Class org/ek9/lang/Exception
           143   191   137   Class org/ek9/lang/Exception
            63   137   138   any

  static {};
    Code:
         0: return

  private void i_init();
    Code:
         0: return
}`
    TryWithMultipleResourcesAndFinally()
      result <- String()

      try
        ->
          resource1 <- TestResource("first")
          resource2 <- TestResource("second")
        result: "OK"
        stdout <- Stdout()
        stdout.println("Try: " + result)
      catch
        -> ex as Exception
        result: "ERROR"
      finally
        stdout <- Stdout()
        stdout.println("Finally executed")

      stdout <- Stdout()
      stdout.println("Result: " + result)

//EOF
