#!ek9
defines module bytecode.test

  defines program

    @BYTECODE: CODE_GENERATION_AGGREGATES: TYPE: "bytecode.test::ComparisonOperators": `public class bytecode.test.ComparisonOperators {
  public bytecode.test.ComparisonOperators();
    Code:
         0: aload_0
         1: invokespecial #CP                  // Method java/lang/Object."<init>":()V
         4: aload_0
         5: invokevirtual #CP                 // Method i_init:()V
         8: return

  public void _main();
    Code:
         0: aconst_null
         1: astore_1
         2: new           #CP                 // class org/ek9/lang/Stdout
         5: dup
         6: invokespecial #CP                 // Method org/ek9/lang/Stdout."<init>":()V
         9: astore_2
        10: aload_2
        11: astore_1
        12: aconst_null
        13: astore_3
        14: iconst_5
        15: invokestatic  #CP                 // Method java/lang/Integer.toString:(I)Ljava/lang/String;
        18: invokestatic  #CP                 // Method org/ek9/lang/Integer._of:(Ljava/lang/String;)Lorg/ek9/lang/Integer;
        21: astore        4
        23: aload         4
        25: astore_3
        26: aconst_null
        27: astore        5
        29: bipush        10
        31: invokestatic  #CP                 // Method java/lang/Integer.toString:(I)Ljava/lang/String;
        34: invokestatic  #CP                 // Method org/ek9/lang/Integer._of:(Ljava/lang/String;)Lorg/ek9/lang/Integer;
        37: astore        6
        39: aload         6
        41: astore        5
        43: aconst_null
        44: astore        7
        46: iconst_5
        47: invokestatic  #CP                 // Method java/lang/Integer.toString:(I)Ljava/lang/String;
        50: invokestatic  #CP                 // Method org/ek9/lang/Integer._of:(Ljava/lang/String;)Lorg/ek9/lang/Integer;
        53: astore        8
        55: aload         8
        57: astore        7
        59: aconst_null
        60: astore        9
        62: aload_3
        63: astore        10
        65: aload         7
        67: astore        11
        69: aload         10
        71: aload         11
        73: invokevirtual #CP                 // Method org/ek9/lang/Integer._eq:(Lorg/ek9/lang/Integer;)Lorg/ek9/lang/Boolean;
        76: astore        12
        78: aload         12
        80: astore        9
        82: aconst_null
        83: astore        13
        85: aload_3
        86: astore        14
        88: aload         5
        90: astore        15
        92: aload         14
        94: aload         15
        96: invokevirtual #CP                 // Method org/ek9/lang/Integer._eq:(Lorg/ek9/lang/Integer;)Lorg/ek9/lang/Boolean;
        99: astore        16
       101: aload         16
       103: astore        13
       105: aload_1
       106: astore        17
       108: aload         9
       110: astore        18
       112: aload         17
       114: aload         18
       116: invokeinterface #CP,  2           // InterfaceMethod org/ek9/lang/StringOutput.println:(Lorg/ek9/lang/Any;)V
       121: aload_1
       122: astore        19
       124: aload         13
       126: astore        20
       128: aload         19
       130: aload         20
       132: invokeinterface #CP,  2           // InterfaceMethod org/ek9/lang/StringOutput.println:(Lorg/ek9/lang/Any;)V
       137: aconst_null
       138: astore        21
       140: aload_3
       141: astore        22
       143: aload         5
       145: astore        23
       147: aload         22
       149: aload         23
       151: invokevirtual #CP                 // Method org/ek9/lang/Integer._neq:(Lorg/ek9/lang/Integer;)Lorg/ek9/lang/Boolean;
       154: astore        24
       156: aload         24
       158: astore        21
       160: aconst_null
       161: astore        25
       163: aload_3
       164: astore        26
       166: aload         7
       168: astore        27
       170: aload         26
       172: aload         27
       174: invokevirtual #CP                 // Method org/ek9/lang/Integer._neq:(Lorg/ek9/lang/Integer;)Lorg/ek9/lang/Boolean;
       177: astore        28
       179: aload         28
       181: astore        25
       183: aload_1
       184: astore        29
       186: aload         21
       188: astore        30
       190: aload         29
       192: aload         30
       194: invokeinterface #CP,  2           // InterfaceMethod org/ek9/lang/StringOutput.println:(Lorg/ek9/lang/Any;)V
       199: aload_1
       200: astore        31
       202: aload         25
       204: astore        32
       206: aload         31
       208: aload         32
       210: invokeinterface #CP,  2           // InterfaceMethod org/ek9/lang/StringOutput.println:(Lorg/ek9/lang/Any;)V
       215: aconst_null
       216: astore        33
       218: aload_3
       219: astore        34
       221: aload         5
       223: astore        35
       225: aload         34
       227: aload         35
       229: invokevirtual #CP                 // Method org/ek9/lang/Integer._lt:(Lorg/ek9/lang/Integer;)Lorg/ek9/lang/Boolean;
       232: astore        36
       234: aload         36
       236: astore        33
       238: aconst_null
       239: astore        37
       241: aload         5
       243: astore        38
       245: aload_3
       246: astore        39
       248: aload         38
       250: aload         39
       252: invokevirtual #CP                 // Method org/ek9/lang/Integer._lt:(Lorg/ek9/lang/Integer;)Lorg/ek9/lang/Boolean;
       255: astore        40
       257: aload         40
       259: astore        37
       261: aload_1
       262: astore        41
       264: aload         33
       266: astore        42
       268: aload         41
       270: aload         42
       272: invokeinterface #CP,  2           // InterfaceMethod org/ek9/lang/StringOutput.println:(Lorg/ek9/lang/Any;)V
       277: aload_1
       278: astore        43
       280: aload         37
       282: astore        44
       284: aload         43
       286: aload         44
       288: invokeinterface #CP,  2           // InterfaceMethod org/ek9/lang/StringOutput.println:(Lorg/ek9/lang/Any;)V
       293: aconst_null
       294: astore        45
       296: aload_3
       297: astore        46
       299: aload         7
       301: astore        47
       303: aload         46
       305: aload         47
       307: invokevirtual #CP                 // Method org/ek9/lang/Integer._lteq:(Lorg/ek9/lang/Integer;)Lorg/ek9/lang/Boolean;
       310: astore        48
       312: aload         48
       314: astore        45
       316: aconst_null
       317: astore        49
       319: aload_3
       320: astore        50
       322: aload         5
       324: astore        51
       326: aload         50
       328: aload         51
       330: invokevirtual #CP                 // Method org/ek9/lang/Integer._lteq:(Lorg/ek9/lang/Integer;)Lorg/ek9/lang/Boolean;
       333: astore        52
       335: aload         52
       337: astore        49
       339: aconst_null
       340: astore        53
       342: aload         5
       344: astore        54
       346: aload_3
       347: astore        55
       349: aload         54
       351: aload         55
       353: invokevirtual #CP                 // Method org/ek9/lang/Integer._lteq:(Lorg/ek9/lang/Integer;)Lorg/ek9/lang/Boolean;
       356: astore        56
       358: aload         56
       360: astore        53
       362: aload_1
       363: astore        57
       365: aload         45
       367: astore        58
       369: aload         57
       371: aload         58
       373: invokeinterface #CP,  2           // InterfaceMethod org/ek9/lang/StringOutput.println:(Lorg/ek9/lang/Any;)V
       378: aload_1
       379: astore        59
       381: aload         49
       383: astore        60
       385: aload         59
       387: aload         60
       389: invokeinterface #CP,  2           // InterfaceMethod org/ek9/lang/StringOutput.println:(Lorg/ek9/lang/Any;)V
       394: aload_1
       395: astore        61
       397: aload         53
       399: astore        62
       401: aload         61
       403: aload         62
       405: invokeinterface #CP,  2           // InterfaceMethod org/ek9/lang/StringOutput.println:(Lorg/ek9/lang/Any;)V
       410: aconst_null
       411: astore        63
       413: aload         5
       415: astore        64
       417: aload_3
       418: astore        65
       420: aload         64
       422: aload         65
       424: invokevirtual #CP                 // Method org/ek9/lang/Integer._gt:(Lorg/ek9/lang/Integer;)Lorg/ek9/lang/Boolean;
       427: astore        66
       429: aload         66
       431: astore        63
       433: aconst_null
       434: astore        67
       436: aload_3
       437: astore        68
       439: aload         5
       441: astore        69
       443: aload         68
       445: aload         69
       447: invokevirtual #CP                 // Method org/ek9/lang/Integer._gt:(Lorg/ek9/lang/Integer;)Lorg/ek9/lang/Boolean;
       450: astore        70
       452: aload         70
       454: astore        67
       456: aload_1
       457: astore        71
       459: aload         63
       461: astore        72
       463: aload         71
       465: aload         72
       467: invokeinterface #CP,  2           // InterfaceMethod org/ek9/lang/StringOutput.println:(Lorg/ek9/lang/Any;)V
       472: aload_1
       473: astore        73
       475: aload         67
       477: astore        74
       479: aload         73
       481: aload         74
       483: invokeinterface #CP,  2           // InterfaceMethod org/ek9/lang/StringOutput.println:(Lorg/ek9/lang/Any;)V
       488: aconst_null
       489: astore        75
       491: aload         5
       493: astore        76
       495: aload_3
       496: astore        77
       498: aload         76
       500: aload         77
       502: invokevirtual #CP                 // Method org/ek9/lang/Integer._gteq:(Lorg/ek9/lang/Integer;)Lorg/ek9/lang/Boolean;
       505: astore        78
       507: aload         78
       509: astore        75
       511: aconst_null
       512: astore        79
       514: aload_3
       515: astore        80
       517: aload         7
       519: astore        81
       521: aload         80
       523: aload         81
       525: invokevirtual #CP                 // Method org/ek9/lang/Integer._gteq:(Lorg/ek9/lang/Integer;)Lorg/ek9/lang/Boolean;
       528: astore        82
       530: aload         82
       532: astore        79
       534: aconst_null
       535: astore        83
       537: aload_3
       538: astore        84
       540: aload         5
       542: astore        85
       544: aload         84
       546: aload         85
       548: invokevirtual #CP                 // Method org/ek9/lang/Integer._gteq:(Lorg/ek9/lang/Integer;)Lorg/ek9/lang/Boolean;
       551: astore        86
       553: aload         86
       555: astore        83
       557: aload_1
       558: astore        87
       560: aload         75
       562: astore        88
       564: aload         87
       566: aload         88
       568: invokeinterface #CP,  2           // InterfaceMethod org/ek9/lang/StringOutput.println:(Lorg/ek9/lang/Any;)V
       573: aload_1
       574: astore        89
       576: aload         79
       578: astore        90
       580: aload         89
       582: aload         90
       584: invokeinterface #CP,  2           // InterfaceMethod org/ek9/lang/StringOutput.println:(Lorg/ek9/lang/Any;)V
       589: aload_1
       590: astore        91
       592: aload         83
       594: astore        92
       596: aload         91
       598: aload         92
       600: invokeinterface #CP,  2           // InterfaceMethod org/ek9/lang/StringOutput.println:(Lorg/ek9/lang/Any;)V
       605: return

  static {};
    Code:
         0: return

  private void i_init();
    Code:
         0: return
}`

    ComparisonOperators()
      stdout <- Stdout()
      a <- 5
      b <- 10
      c <- 5

      // Test equality (==)
      eq1 <- a == c    // true
      eq2 <- a == b    // false
      stdout.println(eq1)
      stdout.println(eq2)

      // Test inequality (<>)
      ne1 <- a <> b    // true
      ne2 <- a <> c    // false
      stdout.println(ne1)
      stdout.println(ne2)

      // Test less than (<)
      lt1 <- a < b     // true
      lt2 <- b < a     // false
      stdout.println(lt1)
      stdout.println(lt2)

      // Test less than or equal (<=)
      lte1 <- a <= c   // true
      lte2 <- a <= b   // true
      lte3 <- b <= a   // false
      stdout.println(lte1)
      stdout.println(lte2)
      stdout.println(lte3)

      // Test greater than (>)
      gt1 <- b > a     // true
      gt2 <- a > b     // false
      stdout.println(gt1)
      stdout.println(gt2)

      // Test greater than or equal (>=)
      gte1 <- b >= a   // true
      gte2 <- a >= c   // true
      gte3 <- a >= b   // false
      stdout.println(gte1)
      stdout.println(gte2)
      stdout.println(gte3)

//EOF
