#!ek9
<?-
  Bytecode test for complete try/catch/finally statement.
  All three parts present: try block, catch handler, finally block.
  Tests exception handling with finally duplication.
-?>
defines module bytecode.test

  defines program

    @BYTECODE: CODE_GENERATION_AGGREGATES: TYPE: "bytecode.test::TryCatchFinally":`public class bytecode.test.TryCatchFinally {
  static {};
    Code:
         0: return

  private void i_init();
    Code:
         0: return

  public bytecode.test.TryCatchFinally();
    Code:
         0: aload_0
         1: invokespecial #CP                 // Method java/lang/Object."<init>":()V
         4: aload_0
         5: invokevirtual #CP                 // Method i_init:()V
         8: return

  public void _main();
    Code:
         0: aconst_null
         1: astore_1
         2: new           #CP                 // class org/ek9/lang/Stdout
         5: dup
         6: invokespecial #CP                 // Method org/ek9/lang/Stdout."<init>":()V
         9: astore_2
        10: aload_2
        11: astore_1
        12: aload_1
        13: astore_3
        14: ldc           #CP                 // String Try block executing
        16: invokestatic  #CP                 // Method org/ek9/lang/String._of:(Ljava/lang/String;)Lorg/ek9/lang/String;
        19: astore        4
        21: aload_3
        22: aload         4
        24: invokevirtual #CP                 // Method org/ek9/lang/Stdout.println:(Lorg/ek9/lang/String;)V
        27: aconst_null
        28: astore        5
        30: bipush        42
        32: invokestatic  #CP                 // Method java/lang/Integer.toString:(I)Ljava/lang/String;
        35: invokestatic  #CP                 // Method org/ek9/lang/Integer._of:(Ljava/lang/String;)Lorg/ek9/lang/Integer;
        38: astore        6
        40: aload         6
        42: astore        5
        44: aload_1
        45: astore        7
        47: aload         5
        49: astore        8
        51: aload         7
        53: aload         8
        55: invokeinterface #CP,  2           // InterfaceMethod org/ek9/lang/StringOutput.println:(Lorg/ek9/lang/Any;)V
        60: aload_1
        61: astore        9
        63: ldc           #CP                 // String Finally block executing
        65: invokestatic  #CP                 // Method org/ek9/lang/String._of:(Ljava/lang/String;)Lorg/ek9/lang/String;
        68: astore        10
        70: aload         9
        72: aload         10
        74: invokevirtual #CP                 // Method org/ek9/lang/Stdout.println:(Lorg/ek9/lang/String;)V
        77: goto          124
        80: astore        11
        82: aload_1
        83: astore        12
        85: ldc           #CP                 // String Catch block executing
        87: invokestatic  #CP                 // Method org/ek9/lang/String._of:(Ljava/lang/String;)Lorg/ek9/lang/String;
        90: astore        13
        92: aload         12
        94: aload         13
        96: invokevirtual #CP                 // Method org/ek9/lang/Stdout.println:(Lorg/ek9/lang/String;)V
        99: goto          124
       102: astore        14
       104: aload_1
       105: astore        9
       107: ldc           #CP                 // String Finally block executing
       109: invokestatic  #CP                 // Method org/ek9/lang/String._of:(Ljava/lang/String;)Lorg/ek9/lang/String;
       112: astore        10
       114: aload         9
       116: aload         10
       118: invokevirtual #CP                 // Method org/ek9/lang/Stdout.println:(Lorg/ek9/lang/String;)V
       121: aload         14
       123: athrow
       124: return
      Exception table:
         from    to  target type
            12    60    80   Class org/ek9/lang/Exception
            12   102   102   any
}`
    TryCatchFinally()
      stdout <- Stdout()

      try
        stdout.println("Try block executing")
        value <- 42
        stdout.println(value)
      catch
        -> ex as Exception
        stdout.println("Catch block executing")
      finally
        stdout.println("Finally block executing")

//EOF
